animeworld/__init__.py
animeworld/anime.py
animeworld/episodio.py
animeworld/exceptions.py
animeworld/setup.py
animeworld/utility.py
animeworld/servers/AnimeWorld_Server.py
animeworld/servers/Server.py
animeworld/servers/Streamtape.py
animeworld/servers/YouTube.py
animeworld/servers/__init__.py
tests/__init__.py
tests/test_animeworld.py
awHyper-1.0.0.dist-info/LICENSE
awHyper-1.0.0.dist-info/METADATA
awHyper-1.0.0.dist-info/WHEEL
awHyper-1.0.0.dist-info/top_level.txt
awHyper-1.0.0.dist-info/RECORD
