Metadata-Version: 2.1
Name: awHyper
Version: 1.0.0
Summary: AnimeWorld UNOFFICIAL API
Home-page: https://mainkronos.github.io/AnimeWorld-API/
Author: MainKronos
License: MIT
Classifier: Programming Language :: Python :: 3
Classifier: License :: OSI Approved :: MIT License
Classifier: Operating System :: OS Independent
Classifier: Topic :: Utilities
Requires-Python: >= 3.7
License-File: LICENSE
Requires-Dist: httpx
Requires-Dist: httpx[http2]
Requires-Dist: youtube-dl
Requires-Dist: beautifulsoup4
